aspcore/__init__.py
aspcore/adaptivefilter.py
aspcore/correlation.py
aspcore/filter.py
aspcore/filterdesign.py
aspcore/filterdynamic.py
aspcore/lowrank.py
aspcore/matrices.py
aspcore/matrices_jax.py
aspcore/montecarlo.py
aspcore/pseq.py
aspcore/utilities.py
aspcore/fouriertransform/__init__.py
aspcore/fouriertransform/chirp_z_transform.py
aspcore/fouriertransform/dft.py
aspcore/fouriertransform/frequencyfiltering.py
aspcore/fouriertransform_jax/__init__.py
aspcore/fouriertransform_jax/dft_jax.py
aspcore-0.0.5.dist-info/licenses/LICENSE
aspcore-0.0.5.dist-info/METADATA
aspcore-0.0.5.dist-info/WHEEL
aspcore-0.0.5.dist-info/top_level.txt
aspcore-0.0.5.dist-info/RECORD
