Metadata-Version: 2.4
Name: aspcore
Version: 0.0.5
Author-email: Jesper Brunnström <jesper_brunnstrom@hotmail.com>
Project-URL: Documentation, https://sounds-research.github.io/aspcore/
Project-URL: Repository, https://github.com/SOUNDS-RESEARCH/aspcore
Classifier: Operating System :: OS Independent
Classifier: Programming Language :: Python :: 3
Classifier: License :: OSI Approved :: MIT License
Requires-Python: >=3.11
License-File: LICENSE
Requires-Dist: numpy
Requires-Dist: scipy
Requires-Dist: numba
Requires-Dist: numexpr
Requires-Dist: jax
Requires-Dist: matplotlib
Requires-Dist: tensorly
Requires-Dist: samplerate
Provides-Extra: test
Requires-Dist: pytest; extra == "test"
Requires-Dist: hypothesis; extra == "test"
Requires-Dist: aspsim; extra == "test"
Provides-Extra: extra
Requires-Dist: tikzplotlib; extra == "extra"
Dynamic: license-file
